nonebot_plugin_ghtiles-0.1.4.dist-info/METADATA
nonebot_plugin_ghtiles-0.1.4.dist-info/WHEEL
nonebot_plugin_ghtiles-0.1.4.dist-info/licenses/LICENSE
nonebot_plugin_ghtiles/__init__.py
nonebot_plugin_ghtiles/config.py
nonebot_plugin_ghtiles/utils.py
nonebot_plugin_ghtiles-0.1.4.dist-info/RECORD
