Metadata-Version: 2.1
Name: nonebot-plugin-ghtiles
Version: 0.1.4
Summary: A nonebot2 plugin for show GitHub contributions
Home-page: https://github.com/Lipraty/nonebot-plugin-ghtiles
Classifier: Programming Language :: Python :: 3
Classifier: License :: OSI Approved :: MIT License
Classifier: Operating System :: OS Independent
Project-URL: Homepage, https://github.com/Lipraty/nonebot-plugin-ghtiles
Requires-Python: <4.0,>=3.9
Requires-Dist: nonebot2>=2.2.0
Requires-Dist: httpx~=0.27
Requires-Dist: nonebot-plugin-alconna>=0.38.1
Requires-Dist: nonebot-plugin-apscheduler~=0.4
Requires-Dist: nonebot-plugin-session~=0.3
Requires-Dist: nonebot-plugin-localstore~=0.6
Requires-Dist: beautifulsoup4>=4.12.3
